imodmodel/__init__.py
imodmodel/binary_specification.py
imodmodel/dataframe.py
imodmodel/functions.py
imodmodel/models.py
imodmodel/parsers.py
imodmodel/writers.py
imodmodel-0.1.0.dist-info/METADATA
imodmodel-0.1.0.dist-info/WHEEL
imodmodel-0.1.0.dist-info/licenses/LICENSE
imodmodel-0.1.0.dist-info/RECORD
