Metadata-Version: 2.4
Name: imodmodel
Version: 0.1.0
Summary: IMOD model files as pandas DataFrames in Python.
Project-URL: homepage, https://github.com/teamtomo/imodmodel
Project-URL: repository, https://github.com/teamtomo/imodmodel
Author: Alister Burt
Author-email: alisterburt@gmail.com
License: BSD 3-Clause License
License-File: LICENSE
Classifier: Development Status :: 3 - Alpha
Classifier: License :: OSI Approved :: BSD License
Classifier: Programming Language :: Python :: 3
Classifier: Programming Language :: Python :: 3.8
Classifier: Programming Language :: Python :: 3.9
Classifier: Programming Language :: Python :: 3.10
Classifier: Programming Language :: Python :: 3.11
Requires-Python: >=3.9
Requires-Dist: numpy
Requires-Dist: pandas
Requires-Dist: pydantic>=2
Provides-Extra: dev
Requires-Dist: black; extra == 'dev'
Requires-Dist: ipython; extra == 'dev'
Requires-Dist: mkdocs-jupyter; extra == 'dev'
Requires-Dist: mkdocs-material; extra == 'dev'
Requires-Dist: mypy; extra == 'dev'
Requires-Dist: pdbpp; extra == 'dev'
Requires-Dist: pre-commit; extra == 'dev'
Requires-Dist: pytest; extra == 'dev'
Requires-Dist: pytest-cov; extra == 'dev'
Requires-Dist: rich; extra == 'dev'
Requires-Dist: ruff; extra == 'dev'
Provides-Extra: test
Requires-Dist: pytest-cov; extra == 'test'
Requires-Dist: pytest>=6.0; extra == 'test'
